[
    {
        "nid": "11",
        "name": "EasternPath (E)",
        "tilemap": "EPE",
        "bg_tilemap": null,
        "party": "Simon",
        "music": {},
        "objective": {
            "simple": "",
            "win": "",
            "loss": ""
        },
        "roam": true,
        "roam_unit": "Simon",
        "go_to_overworld": false,
        "units": [
            {
                "nid": "101",
                "variant": null,
                "level": 1,
                "klass": "Brigand",
                "faction": "Soldier",
                "starting_items": [
                    [
                        "Iron_Mace",
                        false
                    ]
                ],
                "starting_skills": [],
                "team": "enemy",
                "ai": "None",
                "roam_ai": "EPEEnterCave",
                "ai_group": null,
                "starting_position": [
                    10,
                    23
                ],
                "starting_traveler": null,
                "generic": true
            },
            {
                "nid": "Simon",
                "team": "player",
                "ai": "None",
                "roam_ai": null,
                "ai_group": null,
                "starting_position": [
                    0,
                    22
                ],
                "starting_traveler": null,
                "generic": false
            },
            {
                "nid": "102",
                "variant": null,
                "level": 5,
                "klass": "Recruit",
                "faction": "Bandit",
                "starting_items": [
                    [
                        "Iron Lance",
                        false
                    ]
                ],
                "starting_skills": [],
                "team": "enemy",
                "ai": "None",
                "roam_ai": null,
                "ai_group": "EPE1G2",
                "starting_position": [
                    44,
                    14
                ],
                "starting_traveler": null,
                "generic": true
            },
            {
                "nid": "105",
                "variant": null,
                "level": 5,
                "klass": "Recruit",
                "faction": "Bandit",
                "starting_items": [
                    [
                        "Iron Lance",
                        false
                    ]
                ],
                "starting_skills": [],
                "team": "enemy",
                "ai": "None",
                "roam_ai": null,
                "ai_group": "EPE1G1",
                "starting_position": [
                    29,
                    11
                ],
                "starting_traveler": null,
                "generic": true
            },
            {
                "nid": "103",
                "variant": null,
                "level": 5,
                "klass": "Journeyman",
                "faction": "Bandit",
                "starting_items": [
                    [
                        "Iron Axe",
                        false
                    ]
                ],
                "starting_skills": [],
                "team": "enemy",
                "ai": "None",
                "roam_ai": null,
                "ai_group": "EPE1G1",
                "starting_position": [
                    32,
                    16
                ],
                "starting_traveler": null,
                "generic": true
            },
            {
                "nid": "104",
                "variant": null,
                "level": 5,
                "klass": "Journeyman",
                "faction": "Bandit",
                "starting_items": [
                    [
                        "Iron Axe",
                        false
                    ]
                ],
                "starting_skills": [],
                "team": "enemy",
                "ai": "Defend",
                "roam_ai": null,
                "ai_group": "EPE1G2",
                "starting_position": [
                    40,
                    14
                ],
                "starting_traveler": null,
                "generic": true
            },
            {
                "nid": "106",
                "variant": null,
                "level": 2,
                "klass": "Mercenary",
                "faction": "Bandit",
                "starting_items": [
                    [
                        "Iron Sword",
                        false
                    ]
                ],
                "starting_skills": [],
                "team": "enemy",
                "ai": "Defend",
                "roam_ai": null,
                "ai_group": "EPE1G2",
                "starting_position": [
                    42,
                    11
                ],
                "starting_traveler": null,
                "generic": true
            },
            {
                "nid": "107",
                "variant": null,
                "level": 5,
                "klass": "Archer",
                "faction": "Bandit",
                "starting_items": [
                    [
                        "Iron Bow",
                        false
                    ]
                ],
                "starting_skills": [],
                "team": "enemy",
                "ai": "Defend",
                "roam_ai": null,
                "ai_group": "EPE1G2",
                "starting_position": [
                    45,
                    10
                ],
                "starting_traveler": null,
                "generic": true
            },
            {
                "nid": "108",
                "variant": null,
                "level": 5,
                "klass": "Archer",
                "faction": "Bandit",
                "starting_items": [
                    [
                        "Iron Bow",
                        false
                    ]
                ],
                "starting_skills": [],
                "team": "enemy",
                "ai": "Defend",
                "roam_ai": null,
                "ai_group": "EPE1G1",
                "starting_position": [
                    28,
                    13
                ],
                "starting_traveler": null,
                "generic": true
            }
        ],
        "regions": [
            {
                "nid": "EnterCave",
                "region_type": "event",
                "position": [
                    6,
                    29
                ],
                "size": [
                    1,
                    1
                ],
                "sub_nid": "EnterCave",
                "condition": "True",
                "time_left": null,
                "only_once": false,
                "interrupt_move": false
            },
            {
                "nid": "EasternBattle",
                "region_type": "event",
                "position": [
                    25,
                    6
                ],
                "size": [
                    23,
                    14
                ],
                "sub_nid": "EPE1",
                "condition": "True",
                "time_left": null,
                "only_once": true,
                "interrupt_move": true
            }
        ],
        "unit_groups": [],
        "connections": [
            {
                "nid": "LeftSide",
                "level": "7",
                "direction": "LEFT",
                "offset": 0
            }
        ]
    }
]