[
    {
        "name": "Intro",
        "trigger": "level_start",
        "level_nid": "17",
        "condition": "True",
        "commands": [],
        "only_once": false,
        "priority": 20,
        "_source": [
            "show_layer;overlaytiles;immediate",
            "hide_layer;destroyedright;immediate;no_warn",
            "hide_layer;destroyedleft;immediate;no_warn",
            "hide_layer;destroyedtop;immediate;no_warn",
            "hide_layer;destroyedtopright;immediate;no_warn",
            "game_var;FreesHouse1Destroyed;False",
            "game_var;FreesHouse2Destroyed;False",
            "game_var;FreesHouse3Destroyed;False",
            "game_var;FreesHouse4Destroyed;False",
            "game_var;freely_exit;True",
            "# End intro setup",
            "remove_unit;102;immediate",
            "move_unit;Simon;6,19;immediate",
            "move_unit;Simon;8,18",
            "center_cursor;15,13",
            "flicker_cursor;15,13",
            "wait;500",
            "center_cursor;8,9",
            "flicker_cursor;8,9",
            "wait;500",
            "center_cursor;10,1",
            "flicker_cursor;10,1",
            "wait;500",
            "center_cursor;Simon",
            "add_portrait;Simon;Left",
            "speak;Simon;Even here...",
            "trigger_script;Global AppearBySimon;Boudica",
            "add_portrait;Boudica;Right",
            "speak;Boudica;Nowhere on the plains is safe.{w}{br}The villages have either collapsed,{w} or will be soon overrun.",
            "speak;Simon;We have to help them.",
            "speak;Boudica;I am grateful that someone finally can.",
            "multi_remove_portrait;Boudica;Simon",
            "trigger_script;Global GenericPreps",
            "add_unit;Vilge;10,0",
            "center_cursor;Vilge",
            "move_unit;Vilge;10,2",
            "add_portrait;Vilge;Right",
            "speak;Vilge;What a slum.{w} Have any asked to join us?",
            "add_portrait;GenericMage;Left",
            "speak;GenericMage;None.{w} They maintain defiance.",
            "speak;Vilge;A shame.{w} Though, I doubt any of these ingrates{w}{br}would be fit for ascendancy.",
            "speak;GenericMage;I concur.",
            "speak;Vilge;Loot their homes and return to the obelisk.",
            "multi_remove_portrait;Vilge;GenericMage",
            "move_unit;Vilge;10,0",
            "remove_unit;Vilge",
            "center_cursor;Simon"
        ]
    }
]