[
    {
        "name": "E1Escape",
        "trigger": "Escape",
        "level_nid": "6",
        "condition": "True",
        "commands": [
            [
                "hide_layer",
                [
                    "blockreturn"
                ]
            ],
            [
                "move_unit",
                [
                    "Simon (Simon)",
                    "13,36"
                ]
            ],
            [
                "remove_unit",
                [
                    "Luther (Luther)",
                    "immediate"
                ]
            ],
            [
                "add_unit",
                [
                    "Luther (Luther)",
                    "13,36",
                    "immediate",
                    "stack"
                ]
            ],
            [
                "move_unit",
                [
                    "Luther (Luther)",
                    "13,35"
                ]
            ],
            [
                "speak",
                [
                    "Luther",
                    "Good, we're all across the bridge.{w}{br}It'll take some time for them to pursue us."
                ]
            ],
            [
                "speak",
                [
                    "Simon",
                    "..."
                ]
            ],
            [
                "speak",
                [
                    "Luther",
                    "Please, milord.{w} We will return, one day."
                ]
            ],
            [
                "trigger_script",
                [
                    "EndCombatEncounter (Global EndCombatEncounter)"
                ]
            ],
            [
                "remove_region",
                [
                    "E1Escape"
                ]
            ],
            [
                "show_layer",
                [
                    "blockreturn"
                ]
            ],
            [
                "trigger_script",
                [
                    "EndCombatEncounterQuick (Global EndCombatEncounterQuick)"
                ]
            ]
        ],
        "only_once": false,
        "priority": 20
    }
]