[
    {
        "name": "Credits",
        "trigger": null,
        "level_nid": null,
        "condition": "True",
        "commands": [
            [
                "comment",
                [
                    "# Tilesets"
                ]
            ],
            [
                "comment",
                [
                    "# Feaw (Deep Swamp)"
                ]
            ],
            [
                "comment",
                [
                    "# N426 (Improved Castle)"
                ]
            ],
            [
                "comment",
                [
                    "#"
                ]
            ],
            [
                "comment",
                [
                    "# Item icons"
                ]
            ],
            [
                "comment",
                [
                    "# Ironmachine (pikes)"
                ]
            ],
            [
                "comment",
                [
                    "# Topazlight (iron and steel mace)"
                ]
            ],
            [
                "comment",
                [
                    "# Beansy (silver mace)"
                ]
            ],
            [
                "comment",
                [
                    "#"
                ]
            ],
            [
                "comment",
                [
                    "# Map sprites"
                ]
            ],
            [
                "comment",
                [
                    "# Suloir (axe cav)"
                ]
            ],
            [
                "comment",
                [
                    "# Teraspark (sword lord)"
                ]
            ],
            [
                "comment",
                [
                    "# Unknown (magus lord)"
                ]
            ]
        ],
        "only_once": false,
        "priority": 20
    }
]