[
    {
        "nid": "FlowerRecruited",
        "desc": "Was Flower recruited in Frees Village?"
    },
    {
        "nid": "OpenedNikasGrave",
        "desc": "Did Simon and Nika dig up her grave?"
    },
    {
        "nid": "freely_exit",
        "desc": "Can exit from roaming menu?"
    },
    {
        "nid": "TurnwheelEnabled",
        "desc": "Has the turnwheel ever been enabled?"
    },
    {
        "nid": "RevealedBoat",
        "desc": "Spoken to Yusna/Rodger?"
    },
    {
        "nid": "MitziRecruited",
        "desc": "Was Mitzi recruited?"
    },
    {
        "nid": "EbertState",
        "desc": "What is the player's relationship with Ebert?"
    },
    {
        "nid": "StaggerWeaponMaterial",
        "desc": "Used for forging weapons"
    },
    {
        "nid": "DamageWeaponMaterial",
        "desc": "Used for forging weapons"
    },
    {
        "nid": "TriangleWeaponMaterial",
        "desc": "Used for forging weapons"
    },
    {
        "nid": "AccuracyWeaponMaterial",
        "desc": "Used for forging weapons"
    },
    {
        "nid": "TwinsRecruited",
        "desc": "Were the Twins recruited in Port Hull?"
    },
    {
        "nid": "HatshepsutMet",
        "desc": "Was Hatshepsut met in Port Hull?"
    }
]